plexcontentmanager/__init__.py
plexcontentmanager/cli.py
plexcontentmanager/config.py
plexcontentmanager/plex_manager.py
plexcontentmanager-0.1.1.dist-info/LICENSE
plexcontentmanager-0.1.1.dist-info/METADATA
plexcontentmanager-0.1.1.dist-info/WHEEL
plexcontentmanager-0.1.1.dist-info/entry_points.txt
plexcontentmanager-0.1.1.dist-info/top_level.txt
plexcontentmanager-0.1.1.dist-info/RECORD
