Metadata-Version: 2.2
Name: plexcontentmanager
Version: 0.1.1
Summary: A command-line tool for managing and curating Plex Media Server content
Home-page: https://github.com/alexboutros/plexcontentmanager
Author: Alex Boutros
Author-email: alex@aterrible.day
Project-URL: Bug Tracker, https://github.com/alexboutros/plexcontentmanager/issues
Project-URL: Source Code, https://github.com/alexboutros/plexcontentmanager
Project-URL: Documentation, https://github.com/alexboutros/plexcontentmanager#readme
Classifier: Programming Language :: Python :: 3
Classifier: License :: OSI Approved :: MIT License
Classifier: Operating System :: OS Independent
Classifier: Development Status :: 4 - Beta
Classifier: Environment :: Console
Classifier: Topic :: Multimedia :: Video
Classifier: Topic :: Utilities
Requires-Python: >=3.6
License-File: LICENSE
Requires-Dist: plexapi
Requires-Dist: click
Requires-Dist: colorama
Requires-Dist: requests>=2.25.0
Requires-Dist: urllib3<2.0.0
Dynamic: author
Dynamic: author-email
Dynamic: classifier
Dynamic: description
Dynamic: description-content-type
Dynamic: home-page
Dynamic: project-url
Dynamic: requires-dist
Dynamic: requires-python
Dynamic: summary
